PyAudioMixer/Main.py
PyAudioMixer/__init__.py
PyAudioMixer-0.0.4.dist-info/LICENSE
PyAudioMixer-0.0.4.dist-info/METADATA
PyAudioMixer-0.0.4.dist-info/WHEEL
PyAudioMixer-0.0.4.dist-info/top_level.txt
PyAudioMixer-0.0.4.dist-info/RECORD
