Metadata-Version: 2.1
Name: PyAudioMixer
Version: 0.0.4
Summary: Advanced Realtime Software Mixer
Home-page: https://github.com/jpc0/PyAudioMixer
Author: Jean-Pierre Coetzee
Author-email: jeanpierrec19@gmail.com
License: UNKNOWN
Platform: UNKNOWN
Classifier: Programming Language :: Python :: 3
Requires-Python: >=3.6
Requires-Dist: numpy (==1.19.1)
Requires-Dist: PyAudio (==0.2.11)
